metalearning/__init__.py
metalearning/example.py
metalearning/version.py
metalearning-0.1.0.dist-info/METADATA
metalearning-0.1.0.dist-info/WHEEL
metalearning-0.1.0.dist-info/top_level.txt
metalearning-0.1.0.dist-info/RECORD
