Metadata-Version: 2.1
Name: metalearning
Version: 0.1.0
Summary: Meta Learning
Home-page: http://github.io/zhiqingxiao/metalearning
Author: Zhiqing Xiao
Author-email: xzq.xiaozhiqing@gmail.com
Classifier: Programming Language :: Python
Classifier: Intended Audience :: Science/Research
